AUTHORS.rst
CONTRIBUTING.rst
HISTORY.rst
LICENSE
MANIFEST.in
README.rst
setup.cfg
setup.py
coinaddress/__init__.py
coinaddress/cli.py
coinaddress/coinaddress.py
coinaddress/keys.py
coinaddress/utils.py
coinaddress.egg-info/PKG-INFO
coinaddress.egg-info/SOURCES.txt
coinaddress.egg-info/dependency_links.txt
coinaddress.egg-info/entry_points.txt
coinaddress.egg-info/not-zip-safe
coinaddress.egg-info/requires.txt
coinaddress.egg-info/top_level.txt
coinaddress/networks/__init__.py
coinaddress/networks/base.py
coinaddress/networks/bitcoin.py
coinaddress/networks/bitcoin_cash.py
coinaddress/networks/ethereum.py
coinaddress/networks/litecoin.py
coinaddress/networks/registry.py
coinaddress/networks/ripple.py
docs/Makefile
docs/authors.rst
docs/conf.py
docs/contributing.rst
docs/history.rst
docs/index.rst
docs/installation.rst
docs/make.bat
docs/readme.rst
docs/usage.rst
tests/__init__.py
tests/test_coinaddress.py