Metadata-Version: 1.2
Name: coinaddress
Version: 0.1.0
Summary: Crypto address generator from xpub
Home-page: https://github.com/jibrelnetwork/coinaddress
Author: Roman Tolkachyov
Author-email: roman@tolkachyov.name
License: MIT license
Keywords: coinaddress
Platform: UNKNOWN
Classifier: Development Status :: 2 - Pre-Alpha
Classifier: Intended Audience :: Developers
Classifier: License :: OSI Approved :: MIT License
Classifier: Natural Language :: English
Classifier: Programming Language :: Python :: 3
Classifier: Programming Language :: Python :: 3.5
Classifier: Programming Language :: Python :: 3.6
Classifier: Programming Language :: Python :: 3.7
Classifier: Programming Language :: Python :: 3.8
Requires-Python: >=3.5
